zeta/__init__.py
zeta/checkpoint.py
zeta/connection.py
zeta/crypto.py
zeta/headers.py
zeta/py.typed
zeta/utils.py
zeta/z.py
zeta/zeta_types.py
zeta/db/__init__.py
zeta/db/addresses.py
zeta/db/checkpoint.py
zeta/db/connection.py
zeta/db/headers.py
zeta/db/keys.py
zeta/db/prevouts.py
zeta/db/transactions.py
zeta/electrum/__init__.py
zeta/electrum/electrum.py
zeta/electrum/eutils.py
zeta/electrum/metaclient.py
zeta/electrum/servers.py
zeta/sync/__init__.py
zeta/sync/chain.py
zeta/sync/coins.py
zeta/sync/tx_cache.py
riemann_zeta-6.0.0.dist-info/LICENSE
riemann_zeta-6.0.0.dist-info/METADATA
riemann_zeta-6.0.0.dist-info/WHEEL
riemann_zeta-6.0.0.dist-info/top_level.txt
riemann_zeta-6.0.0.dist-info/RECORD
