Metadata-Version: 2.1
Name: riemann-zeta
Version: 6.0.0
Summary: UNKNOWN
Home-page: UNKNOWN
Author: James Prestwich
License: LGPL
Platform: UNKNOWN
Requires-Python: >=3.6
Requires-Dist: connectrum
Requires-Dist: riemann-tx (>=2.0.0)
Requires-Dist: ecdsa
Requires-Dist: pycryptodomex
